logto_dj/__init__.py
logto_dj/authentication.py
logto_dj-0.0.5.dist-info/METADATA
logto_dj-0.0.5.dist-info/WHEEL
logto_dj-0.0.5.dist-info/RECORD
